processing/__init__.py
processing/combination.py
processing/transformation.py
utils/__init__.py
utils/io.py
utils/plot.py
imagemvs-0.0.2.dist-info/METADATA
imagemvs-0.0.2.dist-info/WHEEL
imagemvs-0.0.2.dist-info/top_level.txt
imagemvs-0.0.2.dist-info/RECORD
