Metadata-Version: 2.1
Name: imagemvs
Version: 0.0.2
Summary: DIO project process
Home-page: https://github.com/marcosmvsfut/Dio_Unimed_Bootcamp
Author: Marcos Vinicius
Author-email: marcos_mvs99@hotmail.com
Requires-Python: >=3.8
Requires-Dist: matplotlib
Requires-Dist: numpy
Requires-Dist: scikit-image (>=0.16.1)
